truss/__init__.py
truss_shim-0.10.0rc3.dist-info/METADATA
truss_shim-0.10.0rc3.dist-info/WHEEL
truss_shim-0.10.0rc3.dist-info/entry_points.txt
truss_shim-0.10.0rc3.dist-info/RECORD
